{
  "accounts": {
    "luyl": {
      "expected_volatility": 0.05,
      "portfolio_multiplier": 3356.243048000812,
      "strategies": [
        {
          "allocation": 0.8545162641474545,
          "class_name": "CincoStrategy",
          "fixed_size": 8,
          "key": "CincoStrategy_ETH",
          "vt_symbol": "ETHUSDT_SWAP_OKX.GLOBAL"
        }
      ],
      "strategy_count": 1
    },
    "nav": {
      "expected_volatility": 0.1,
      "portfolio_multiplier": 10.660701096997844,
      "strategies": [
        {
          "allocation": 1.2700271963871483,
          "class_name": "CincoStrategy",
          "fixed_size": 12,
          "key": "CincoStrategy_ETH",
          "vt_symbol": "ETHUSDT_SWAP_OKX.GLOBAL"
        },
        {
          "allocation": 5.095357658017067,
          "class_name": "XauIntradayStrategy",
          "fixed_size": 50,
          "key": "XauIntradayStrategy_XAU",
          "vt_symbol": "XAUUSDT_SWAP_OKX.GLOBAL"
        },
        {
          "allocation": 1.3905286203012306,
          "class_name": "TripleRsiLongShortStrategy",
          "fixed_size": 13,
          "key": "TripleRsiLongShort_BTC",
          "vt_symbol": "BTCUSDT_SWAP_OKX.GLOBAL"
        }
      ],
      "strategy_count": 3
    }
  },
  "asset": "crypto",
  "checksums": {
    "luyl": "142185246ca6b436",
    "nav": "d439e35e2da64169"
  },
  "generated_at": "2026-05-13T08:23:55.175298+00:00",
  "sources": {
    "cta_developer_commit": "fd6956d",
    "tracker_commit": "96fc2bd"
  },
  "version": "1.0.0"
}
